{"chunk_definitions":[{"chunk_id":"c2341ut2xpqjd","chunk_label":"unnamed-chunk-1","document_id":"9F5293B2","expansion_state":0,"options":{"engine":"r","eval":false,"label":"unnamed-chunk-84"},"row":52,"row_count":1,"visible":true},{"chunk_id":"ctc6f3bthnt00","chunk_label":"unnamed-chunk-2","document_id":"9F5293B2","expansion_state":0,"options":{"engine":"r","label":"unnamed-chunk-66"},"row":62,"row_count":1,"visible":true},{"chunk_id":"cmkaa7lep2dow","chunk_label":"unnamed-chunk-4","document_id":"9F5293B2","expansion_state":0,"options":{"engine":"r","label":"unnamed-chunk-88"},"row":108,"row_count":1,"visible":true},{"chunk_id":"cwb7c4t4rvsp5","chunk_label":"unnamed-chunk-5","document_id":"9F5293B2","expansion_state":0,"options":{"engine":"r","label":"unnamed-chunk-64"},"row":114,"row_count":1,"visible":true},{"chunk_id":"cpf1fsulq0fl7","chunk_label":"unnamed-chunk-6","document_id":"9F5293B2","expansion_state":0,"options":{"engine":"r","label":"unnamed-chunk-65"},"row":120,"row_count":1,"visible":true},{"chunk_id":"c714g19073ulu","chunk_label":"unnamed-chunk-7","document_id":"9F5293B2","expansion_state":0,"options":{"engine":"r","eval":false,"label":"unnamed-chunk-74"},"row":165,"row_count":1,"visible":true},{"chunk_id":"cw0dp5boj7s77","chunk_label":"unnamed-chunk-8","document_id":"9F5293B2","expansion_state":0,"options":{"engine":"r","eval":false,"label":"unnamed-chunk-68"},"row":228,"row_count":1,"visible":true}],"doc_write_time":1580021203}